justpub/__init__.py
justpub/justpub.py
justpub-0.1.2.dist-info/METADATA
justpub-0.1.2.dist-info/WHEEL
justpub-0.1.2.dist-info/entry_points.txt
justpub-0.1.2.dist-info/top_level.txt
justpub-0.1.2.dist-info/RECORD
