Metadata-Version: 2.1
Name: justpub
Version: 0.1.2
Summary: Publish your python module to pypi with merely one command. 
Home-page: https://github.com/Buggist/Just-Pub
Author: buggist
Author-email: 316114933@qq.com
Classifier: Programming Language :: Python :: 3
Classifier: License :: OSI Approved :: MIT License
Classifier: Operating System :: OS Independent
Requires-Dist: setuptools
Requires-Dist: twine
Requires-Dist: wheel
